watersnake.libs/libwfa2-1265cb7b.so.0
watersnake-0.1.0.dist-info/top_level.txt
watersnake-0.1.0.dist-info/METADATA
watersnake-0.1.0.dist-info/RECORD
watersnake-0.1.0.dist-info/LICENSE
watersnake-0.1.0.dist-info/WHEEL
watersnake/_aligner.c
watersnake/__init__.py
watersnake/_aligner.cpython-311-x86_64-linux-gnu.so
