Metadata-Version: 2.1
Name: watersnake
Version: 0.1.0
Summary: Minimal WFA2-lib wrapper in Python
Author-email: Travis Wrightsman <tw493@cornell.edu>
License: Copyright © 2023 Travis Wrightsman
Project-URL: Homepage, https://github.com/twrightsman/watersnake
Project-URL: Bug Tracker, https://github.com/twrightsman/watersnake/issues
Classifier: Programming Language :: Python :: 3
Classifier: License :: OSI Approved :: MIT License
Requires-Python: >=3.8
License-File: LICENSE
